apphb/__init__.py
apphb/logging.py
test/__init__.py
test/test_heartbeat.py
test/test_logging.py
apphb-0.1.1.dist-info/LICENSE
apphb-0.1.1.dist-info/METADATA
apphb-0.1.1.dist-info/WHEEL
apphb-0.1.1.dist-info/top_level.txt
apphb-0.1.1.dist-info/RECORD
