Metadata-Version: 2.1
Name: apphb
Version: 0.1.1
Summary: Application heartbeats
Home-page: https://github.com/libheartbeats/apphb-python
Author: Connor Imes
Keywords: heartbeats,profiling
Classifier: Topic :: System :: Monitoring
Classifier: Topic :: Utilities
Requires-Python: >=3.7
License-File: LICENSE
